gsselect/__init__.py
gsselect/gemcats.py
gsselect/gsselect.py
gsselect/inpoly.py
gsselect/parangle.py
gsselect-1.3.2.dist-info/LICENSE
gsselect-1.3.2.dist-info/METADATA
gsselect-1.3.2.dist-info/WHEEL
gsselect-1.3.2.dist-info/top_level.txt
gsselect-1.3.2.dist-info/RECORD
