Metadata-Version: 2.1
Name: gsselect
Version: 1.3.2
Summary: Gemini guide star selection and URL target-of-opportunity (TOO) triggering
Home-page: https://github.com/bryanmiller/gsselect
Author: Bryan Miller
Author-email: millerwbryan@gmail.com
License: UNKNOWN
Platform: UNKNOWN
Classifier: Programming Language :: Python
Classifier: Intended Audience :: Science/Research
Classifier: License :: Other/Proprietary License
Classifier: Operating System :: OS Independent
License-File: LICENSE
Requires-Dist: astropy
Requires-Dist: matplotlib
Requires-Dist: numpy (>=1.15.4)
Requires-Dist: rerequests
